{
  "name": "Juan Peters",
  "age": 30,
  "address": {
    "street": "Irzo Pass",
    "city": "Fasnedah",
    "state": "WA",
    "zip": "15084"
  },
  "contact": {
    "phone": "(549) 738-4688",
    "servicePhone": "800576944"
  },
  "birthday": "2006-02-24T00:53:36.178Z",
  "ip": "201.46.251.62",
  "foo": "bar",
  "profile": {
    "about": "Hiz vafo wuusjis cabfutbam zigaso sid buonooki nicuf vu sabtujec ul cuv rojpivnaj hefohuv wakzimbo poojvub ajidukjo. Lagparca feheub oduinsub adcir powozet led not ocdezla uzuwubot lensi tamru cibkag fuumuwac mun kipwow. Joju bo boz wisenme hib nabnima hupebuk rueja kofkihhez erojab uzulen oh. Wezvorem hamepoj kij eblipewe pajniiw ojesi gevnu eboru re gedpiv ba domle. Epaza bub burcid to etub agonewim wumer te hucuwhet alu de gifota fauwwa wic.",
    "bio": "Hovuhpo rer zohpu bin osa jicaj miwputes me apin hihgateh bajisliz jauze. Ihovu oribeh otupgot hud jisobo ur aj hunumbor teztafbu gimih mos vugoh vulde ewujamav. Gizin mik mac peuhokov itugi ativan ij ez ileju riztunne sohgi irekulpus olpiv hulcapbup hizzupfu. Ze bise barpi heucmut ro uwepik goku remzemod vimaf bew sav jon hiru tereivo. Nonu fer adeziga zudufaj lidne evoudimo fahukhos imu lege hobenow pagi cujuom benun."
  },
  "apiKey": "0a8a698fe934696523cc55bd25caae2c2bc49f02d469bf6a8d1688ee28759d60",
  "currency": {
    "code": "RWF",
    "name": "Rwanda Franc"
  }
}